{
    "axes": {
        "axes": [
            {
                "defaultValue": 400,
                "label": "Weight",
                "maxValue": 900,
                "minValue": 100,
                "name": "weight",
                "tag": "wght"
            }
        ]
    },
    "fontInfo": {
        "familyName": "FONTE-RAT"
    },
    "sources": {
        "167ea7a9": {
            "lineMetricsHorizontalLayout": {
                "ascender": {
                    "value": 800,
                    "zone": 16
                },
                "baseline": {
                    "value": 0,
                    "zone": -16
                },
                "capHeight": {
                    "value": 750,
                    "zone": 16
                },
                "descender": {
                    "value": -250,
                    "zone": -16
                },
                "xHeight": {
                    "value": 500,
                    "zone": 16
                }
            },
            "location": {
                "weight": 400
            },
            "name": "Regular"
        },
        "93e169c0": {
            "italicAngle": "20",
            "lineMetricsHorizontalLayout": {
                "ascender": {
                    "value": 800,
                    "zone": 16
                },
                "baseline": {
                    "value": 0,
                    "zone": -16
                },
                "capHeight": {
                    "value": 750,
                    "zone": 16
                },
                "descender": {
                    "value": -250,
                    "zone": -16
                },
                "xHeight": {
                    "value": 500,
                    "zone": 16
                }
            },
            "location": {
                "weight": 500
            },
            "name": "Italic"
        },
        "f0e98463": {
            "lineMetricsHorizontalLayout": {
                "ascender": {
                    "value": 800,
                    "zone": 16
                },
                "baseline": {
                    "value": 0,
                    "zone": -16
                },
                "capHeight": {
                    "value": 750,
                    "zone": 16
                },
                "descender": {
                    "value": -250,
                    "zone": -16
                },
                "xHeight": {
                    "value": 500,
                    "zone": 16
                }
            },
            "location": {
                "weight": 900
            },
            "name": "Black"
        }
    }
}